avro_to_python_types/__init__.py
avro_to_python_types/constants.py
avro_to_python_types/generate_typed_dict.py
avro_to_python_types/py.typed
avro_to_python_types/schema_mapping.py
avro_to_python_types/typed_dict_from_schema.py
avro_to_python_types-0.12.1.dist-info/entry_points.txt
avro_to_python_types-0.12.1.dist-info/LICENSE.txt
avro_to_python_types-0.12.1.dist-info/WHEEL
avro_to_python_types-0.12.1.dist-info/METADATA
avro_to_python_types-0.12.1.dist-info/RECORD
