Metadata-Version: 2.1
Name: avro-to-python-types
Version: 0.12.1
Summary: A library for converting avro schemas to python types.
Home-page: https://github.com/waveaccounting/avro-to-python-types
License: MIT
Keywords: avro,codegen,avro schema,typegen
Author: Dan Green-Leipciger
Requires-Python: >=3.8,<4.0
Classifier: License :: OSI Approved :: MIT License
Classifier: Programming Language :: Python :: 3
Classifier: Programming Language :: Python :: 3.10
Classifier: Programming Language :: Python :: 3.8
Classifier: Programming Language :: Python :: 3.9
Requires-Dist: fastavro (>=1.4.4,<2.0.0)
Project-URL: Repository, https://github.com/waveaccounting/avro-to-python-types
